mnl_punct_norm/__init__.py
mnl_punct_norm/normalizer.py
mnl_punct_norm-0.0.7.dist-info/LICENSE.txt
mnl_punct_norm-0.0.7.dist-info/METADATA
mnl_punct_norm-0.0.7.dist-info/WHEEL
mnl_punct_norm-0.0.7.dist-info/top_level.txt
mnl_punct_norm-0.0.7.dist-info/RECORD
